pydocextractor/__init__.py
pydocextractor/app/__init__.py
pydocextractor/app/image_context.py
pydocextractor/app/service.py
pydocextractor/cli.py
pydocextractor/domain/__init__.py
pydocextractor/domain/config.py
pydocextractor/domain/errors.py
pydocextractor/domain/models.py
pydocextractor/domain/ports.py
pydocextractor/domain/profilers/__init__.py
pydocextractor/domain/profilers/table_profiler.py
pydocextractor/domain/rules.py
pydocextractor/factory.py
pydocextractor/infra/__init__.py
pydocextractor/infra/config/__init__.py
pydocextractor/infra/config/env_loader.py
pydocextractor/infra/extractors/__init__.py
pydocextractor/infra/extractors/chunked_parallel_adapter.py
pydocextractor/infra/extractors/docling_adapter.py
pydocextractor/infra/extractors/pandas_csv_adapter.py
pydocextractor/infra/extractors/pandas_excel_adapter.py
pydocextractor/infra/extractors/pdfplumber_adapter.py
pydocextractor/infra/extractors/pymupdf4llm_adapter.py
pydocextractor/infra/llm/__init__.py
pydocextractor/infra/llm/openai_adapter.py
pydocextractor/infra/llm/resilient_describer.py
pydocextractor/infra/policy/__init__.py
pydocextractor/infra/policy/heuristics.py
pydocextractor/infra/scoring/__init__.py
pydocextractor/infra/scoring/default_scorer.py
pydocextractor/infra/templates/__init__.py
pydocextractor/infra/templates/engines.py
pydocextractor/infra/templates/templates/default.j2
pydocextractor/infra/templates/templates/simple.j2
pydocextractor/infra/templates/templates/tabular.j2
pydocextractor/py.typed
pydocextractor-0.1.11.dist-info/METADATA
pydocextractor-0.1.11.dist-info/WHEEL
pydocextractor-0.1.11.dist-info/entry_points.txt
pydocextractor-0.1.11.dist-info/licenses/LICENSE
pydocextractor-0.1.11.dist-info/RECORD
