Metadata-Version: 2.4
Name: pydocextractor
Version: 0.1.11
Summary: A Python library for converting documents (PDF, DOCX, XLSX) to Markdown with multiple precision levels
Project-URL: Homepage, https://github.com/aminitech/pyDocExtractor
Project-URL: Documentation, https://github.com/aminitech/pyDocExtractor#readme
Project-URL: Repository, https://github.com/aminitech/pyDocExtractor
Project-URL: Issues, https://github.com/aminitech/pyDocExtractor/issues
Author-email: Leonardo Araujo <leo@amini.ai>
License: MIT License
Keywords: conversion,document,extractor,markdown,pdf
Classifier: Development Status :: 3 - Alpha
Classifier: Intended Audience :: Developers
Classifier: License :: OSI Approved :: MIT License
Classifier: Programming Language :: Python :: 3
Classifier: Programming Language :: Python :: 3.11
Classifier: Programming Language :: Python :: 3.12
Requires-Python: >=3.11
Requires-Dist: jinja2>=3.1
Requires-Dist: typing-extensions>=4.12
Requires-Dist: xlrd>=2.0.2
Provides-Extra: all
Requires-Dist: click>=8.0.0; extra == 'all'
Requires-Dist: docling>=2.57.0; extra == 'all'
Requires-Dist: httpx>=0.27.0; extra == 'all'
Requires-Dist: openpyxl>=3.1; extra == 'all'
Requires-Dist: pandas>=2.2; extra == 'all'
Requires-Dist: pdfplumber>=0.7.0; extra == 'all'
Requires-Dist: pillow>=10.0.0; extra == 'all'
Requires-Dist: pymupdf4llm>=0.0.5; extra == 'all'
Requires-Dist: pymupdf>=1.23.0; extra == 'all'
Requires-Dist: python-docx>=1.1; extra == 'all'
Requires-Dist: python-dotenv>=1.0.0; extra == 'all'
Requires-Dist: rich>=13.0.0; extra == 'all'
Requires-Dist: typer>=0.12.5; extra == 'all'
Provides-Extra: cli
Requires-Dist: click>=8.0.0; extra == 'cli'
Requires-Dist: rich>=13.0.0; extra == 'cli'
Requires-Dist: typer>=0.12.5; extra == 'cli'
Provides-Extra: dev
Requires-Dist: import-linter>=2.1; extra == 'dev'
Requires-Dist: mypy>=1.8.0; extra == 'dev'
Requires-Dist: pytest-asyncio>=0.23.0; extra == 'dev'
Requires-Dist: pytest-bdd>=7.0.0; extra == 'dev'
Requires-Dist: pytest-benchmark>=4.0.0; extra == 'dev'
Requires-Dist: pytest-cov>=4.0.0; extra == 'dev'
Requires-Dist: pytest>=8.0.0; extra == 'dev'
Requires-Dist: ruff>=0.14.0; extra == 'dev'
Requires-Dist: types-jinja2>=2.11.0; extra == 'dev'
Provides-Extra: doc
Requires-Dist: docling>=2.57.0; extra == 'doc'
Provides-Extra: docx
Requires-Dist: python-docx>=1.1; extra == 'docx'
Provides-Extra: llm
Requires-Dist: httpx>=0.27.0; extra == 'llm'
Requires-Dist: pillow>=10.0.0; extra == 'llm'
Requires-Dist: python-dotenv>=1.0.0; extra == 'llm'
Provides-Extra: pdf
Requires-Dist: pdfplumber>=0.7.0; extra == 'pdf'
Requires-Dist: pymupdf4llm>=0.0.5; extra == 'pdf'
Requires-Dist: pymupdf>=1.23.0; extra == 'pdf'
Provides-Extra: xlsx
Requires-Dist: openpyxl>=3.1; extra == 'xlsx'
Requires-Dist: pandas>=2.2; extra == 'xlsx'
